surpyval/__init__.py
surpyval/beta/__init__.py
surpyval/competing_risks/__init__.py
surpyval/competing_risks/competing_risks.py
surpyval/competing_risks/competing_risks_proportional_hazard.py
surpyval/competing_risks/fine_gray.py
surpyval/datasets/__init__.py
surpyval/datasets/bofors_steel.csv
surpyval/datasets/boston.csv
surpyval/datasets/heart.csv
surpyval/datasets/lung.csv
surpyval/datasets/rossi.csv
surpyval/datasets/rossi_tv.csv
surpyval/datasets/tires.csv
surpyval/nonparametric/__init__.py
surpyval/nonparametric/filliben.py
surpyval/nonparametric/fleming_harrington.py
surpyval/nonparametric/kaplan_meier.py
surpyval/nonparametric/nelson_aalen.py
surpyval/nonparametric/nonparametric.py
surpyval/nonparametric/nonparametric_fitter.py
surpyval/nonparametric/plotting_positions.py
surpyval/nonparametric/rank_adjust.py
surpyval/nonparametric/success_run.py
surpyval/nonparametric/turnbull.py
surpyval/parametric/__init__.py
surpyval/parametric/bernoulli.py
surpyval/parametric/beta.py
surpyval/parametric/dist_from_hazard.py
surpyval/parametric/exact_event_time.py
surpyval/parametric/expo_weibull.py
surpyval/parametric/exponential.py
surpyval/parametric/gamma.py
surpyval/parametric/gumbel.py
surpyval/parametric/gumbel_lev.py
surpyval/parametric/logistic.py
surpyval/parametric/loglogistic.py
surpyval/parametric/lognormal.py
surpyval/parametric/mixture_model.py
surpyval/parametric/normal.py
surpyval/parametric/parallel.py
surpyval/parametric/parametric.py
surpyval/parametric/parametric_fitter.py
surpyval/parametric/rayleigh.py
surpyval/parametric/series.py
surpyval/parametric/uniform.py
surpyval/parametric/weibull.py
surpyval/parametric/fitters/__init__.py
surpyval/parametric/fitters/mle.py
surpyval/parametric/fitters/mom.py
surpyval/parametric/fitters/mpp.py
surpyval/parametric/fitters/mps.py
surpyval/parametric/fitters/mse.py
surpyval/regression/__init__.py
surpyval/regression/accelerated_failure_time.py
surpyval/regression/cox_ph.py
surpyval-0.10.10.dist-info/LICENSE
surpyval-0.10.10.dist-info/METADATA
surpyval-0.10.10.dist-info/WHEEL
surpyval-0.10.10.dist-info/top_level.txt
surpyval-0.10.10.dist-info/RECORD
