Metadata-Version: 2.1
Name: surpyval
Version: 0.10.10
Summary: A python package for survival analysis
Home-page: https://github.com/derrynknife/SurPyval
Author: Derryn Knife
Author-email: derryn@reliafy.com
Classifier: Programming Language :: Python :: 3
Classifier: License :: OSI Approved :: MIT License
Classifier: Operating System :: OS Independent
Requires-Python: >=3.6
License-File: LICENSE
Requires-Dist: autograd
Requires-Dist: numpy
Requires-Dist: scipy
Requires-Dist: pandas
Requires-Dist: autograd-gamma
Requires-Dist: matplotlib
Requires-Dist: numpy-indexed
Requires-Dist: numba
Requires-Dist: formulaic
